.DS_Store
bitbar/__init__.py
bitbar-2020.7.72.dist-info/LICENSE
bitbar-2020.7.72.dist-info/METADATA
bitbar-2020.7.72.dist-info/WHEEL
bitbar-2020.7.72.dist-info/top_level.txt
bitbar-2020.7.72.dist-info/RECORD
