Metadata-Version: 2.1
Name: bitbar
Version: 2020.7.72
Summary: bitbar python pkg
Home-page: https://github.com/leohu1/bitbar
Author: huqiwei
Author-email: 2607131406@qq.com
License: UNKNOWN
Platform: UNKNOWN
Classifier: Programming Language :: Python :: 3
Classifier: Operating System :: OS Independent
Requires-Python: >=3.6
